django_vladik_select2/__init__.py
django_vladik_select2/apps.py
django_vladik_select2/urls.py
django_vladik_select2/views.py
django_vladik_select2/widgets.py
django_vladik_select2/static/django_vladik_select2/css/vladik-select2.css
django_vladik_select2/static/django_vladik_select2/js/vladik-select2.js
django_vladik_select2/templates/widgets/vladik-select2.html
django_vladik_select2-0.1.0.dist-info/licenses/LICENSE
django_vladik_select2-0.1.0.dist-info/METADATA
django_vladik_select2-0.1.0.dist-info/WHEEL
django_vladik_select2-0.1.0.dist-info/top_level.txt
django_vladik_select2-0.1.0.dist-info/RECORD
