Metadata-Version: 2.4
Name: django-vladik-select2
Version: 0.1.0
Summary: Select2 para Django con dependencias dinámicas y re-init en modales
Author-email: Vladik Muñoz <vladikma87@gmail.com>
License: MIT License
Project-URL: Homepage, https://github.com/vladikma/django-vladik-select2
Requires-Python: >=3.8
License-File: LICENSE
Requires-Dist: Django>=3.2
Requires-Dist: django-widget-tweaks
Dynamic: license-file
